[
  {
    "building": "MGH",
    "floor": "First Floor",
    "stall":"Private Room",
    "rating": "4"
  },
  {
    "building": "ODE",
    "floor": "Second Floor",
    "rating": "2"
  },
  {
    "building": "KNE",
    "floor": "Second Floor",
    "rating": "5"
  },
  {
    "building": "GWN",
    "floor": "First Floor",
    "rating": "3"
  },
  {
    "building": "ODE",
    "floor": "Individual Floor",
    "rating": "1"
  },
  {
    "building": "KNE",
    "floor": "Basement",
    "rating": "4"
  },
  {
    "building": "MGH",
    "floor": "Third Floor",
    "rating": "5"
  }
]